[
    {
        "_is_template": true,

        "check_interval": 15,
        "check_period": "24x7",
        "max_check_attempts": 3,
        "retry_interval": 1,

        "_realm": "All",
        "_sub_realm": true,
        "aggregation": "mysql",
        "active_checks_enabled": true,
        "alias": "",
        "host": "_dummy",
        "imported_from": "alignak-checks-mysql",
        "initial_state": "x",
        "name": "mysql-service",
        "notes": "",
        "notes_url": "",
        "tags": [
            "Mysql"
        ]
    },
    {
        "_is_template": true,
        "_templates": [
            "mysql-service"
        ],
        "alias": "Connection (alive)",
        "check_command": "check_mysql_connection",
        "check_command_args": "",
        "host": "generic-mysql",
        "name": "Mysql-connection"
    },
    {
        "_is_template": true,
        "_templates": [
            "mysql-service"
        ],
        "alias": "Restart",
        "check_command": "check_mysql_uptime",
        "check_command_args": "",
        "host": "generic-mysql",
        "name": "Mysql-restart"
    },
    {
        "_is_template": true,
        "_templates": [
            "mysql-service"
        ],
        "alias": "Buffer pool wait free",
        "aggregation": "mysql/innodb",
        "check_command": "check_mysql_bufferpool_wait_free",
        "check_command_args": "",
        "host": "generic-mysql",
        "name": "Mysql-buffer-pool-wait-free"
    },
    {
        "_is_template": true,
        "_templates": [
            "mysql-service"
        ],
        "alias": "Log waits",
        "aggregation": "mysql/innodb",
        "check_command": "check_mysql_log_waits",
        "check_command_args": "",
        "host": "generic-mysql",
        "name": "Mysql-log-waits"
    },
    {
        "_is_template": true,
        "_templates": [
            "mysql-service"
        ],
        "alias": "Index usage",
        "check_command": "check_mysql_index_usage",
        "check_command_args": "",
        "host": "generic-mysql",
        "name": "Mysql-index-usage"
    },
    {
        "_is_template": true,
        "_templates": [
            "mysql-service"
        ],
        "alias": "Long running processes",
        "check_command": "check_mysql_long_running_procs",
        "check_command_args": "",
        "host": "generic-mysql",
        "name": "Mysql-long-running-processes"
    },
    {
        "_is_template": true,
        "_templates": [
            "mysql-service"
        ],
        "alias": "Opened files",
        "check_command": "check_mysql_open_files",
        "check_command_args": "",
        "host": "generic-mysql",
        "name": "Mysql-opened-files"
    },
    {
        "_is_template": true,
        "_templates": [
            "mysql-service"
        ],
        "alias": "Slow queries",
        "check_command": "check_mysql_slow_queries",
        "check_command_args": "",
        "host": "generic-mysql",
        "name": "Mysql-slow-queries"
    },
    {
        "_is_template": true,
        "_templates": [
            "mysql-service"
        ],
        "alias": "Table locks contention",
        "check_command": "check_mysql_table_lock_contention",
        "check_command_args": "",
        "host": "generic-mysql",
        "name": "Mysql-table-lock-contention"
    },
    {
        "_is_template": true,
        "_templates": [
            "mysql-service"
        ],
        "alias": "Query cache hit rate",
        "aggregation": "mysql/cache",
        "check_command": "check_mysql_qcache_hitrate",
        "check_command_args": "",
        "host": "generic-mysql",
        "name": "Mysql-qcache-hit-rate"
    },
    {
        "_is_template": true,
        "_templates": [
            "mysql-service"
        ],
        "alias": "Query cache low memory prune",
        "aggregation": "mysql/cache",
        "check_command": "check_mysql_qcache_lowmem_prunes",
        "check_command_args": "",
        "host": "generic-mysql",
        "name": "Mysql-qcache-low-mem-prune"
    },
    {
        "_is_template": true,
        "_templates": [
            "mysql-service"
        ],
        "alias": "Query cache hit rate",
        "aggregation": "mysql/cache",
        "check_command": "check_mysql_keycache_hitrate",
        "check_command_args": "",
        "host": "generic-mysql",
        "name": "Mysql-keycache-hit-rate"
    },
    {
        "_is_template": true,
        "_templates": [
            "mysql-service"
        ],
        "alias": "Buffer pool hit rate",
        "aggregation": "mysql/cache",
        "check_command": "check_mysql_bufferpool_hitrate",
        "check_command_args": "",
        "host": "generic-mysql",
        "name": "Mysql-buffer-pool-hit-rate"
    },
    {
        "_is_template": true,
        "_templates": [
            "mysql-service"
        ],
        "alias": "Table cache hit rate",
        "aggregation": "mysql/cache",
        "check_command": "check_mysql_tablecache_hitrate",
        "check_command_args": "",
        "host": "generic-mysql",
        "name": "Mysql-table-cache-hit-rate"
    },
    {
        "_is_template": true,
        "_templates": [
            "mysql-service"
        ],
        "alias": "Thread cache hit rate",
        "aggregation": "mysql/cache",
        "check_command": "check_mysql_threadcache_hitrate",
        "check_command_args": "",
        "host": "generic-mysql",
        "name": "Mysql-thread-cache-hit-rate"
    },
    {
        "_is_template": true,
        "_templates": [
            "mysql-service"
        ],
        "alias": "Threads connected",
        "check_command": "check_mysql_threads_connected",
        "check_command_args": "",
        "host": "generic-mysql",
        "name": "Mysql-threads-connected"
    },
    {
        "_is_template": true,
        "_templates": [
            "mysql-service"
        ],
        "alias": "Temporary tables on disk",
        "check_command": "check_mysql_tmp_disk_tables",
        "check_command_args": "",
        "host": "generic-mysql",
        "name": "Mysql-tmp-disk-tables"
    },
    {
        "_is_template": true,
        "_templates": [
            "mysql-service"
        ],
        "aggregation": "mysql/replication",
        "alias": "Slave lag",
        "check_command": "check_mysql_slave_lag",
        "check_command_args": "",
        "host": "mysql-slave",
        "name": "Mysql-tmp-disk-tables"
    },
    {
        "_is_template": true,
        "_templates": [
            "mysql-service"
        ],
        "aggregation": "mysql/replication",
        "alias": "Slave SQL running",
        "check_command": "check_mysql_slave_sql_running",
        "check_command_args": "",
        "host": "mysql-slave",
        "name": "Mysql-slave-sql-running"
    },
    {
        "_is_template": true,
        "_templates": [
            "mysql-service"
        ],
        "aggregation": "mysql/replication",
        "alias": "Slave I/O running",
        "check_command": "check_mysql_slave_io_running",
        "check_command_args": "",
        "host": "mysql-slave",
        "name": "Mysql-slave-io-running"
    },
    {
        "_is_template": true,
        "_templates": [
            "mysql-service"
        ],
        "aggregation": "mysql/cluster",
        "alias": "Cluster nbdb running",
        "check_command": "check_mysql_cluster_ndbd_running",
        "check_command_args": "",
        "host": "mysql-cluster",
        "name": "Mysql-tmpnbdb-running"
    }
]